excel_operate/__init__.py
excel_operate/excel_operate/__init__.py
excel_operate/excel_operate/excel_operate.py
excel_operate/list_operate/__init__.py
excel_operate/list_operate/list_operate.py
excel_operate/sheet_comparison/__init__.py
excel_operate/sheet_comparison/sheet_comparison.py
excel_operate/sheet_copy/__init__.py
excel_operate/sheet_copy/sheet_copy.py
excel_operate_light22-2.1.2.dist-info/LICENSE
excel_operate_light22-2.1.2.dist-info/METADATA
excel_operate_light22-2.1.2.dist-info/WHEEL
excel_operate_light22-2.1.2.dist-info/top_level.txt
excel_operate_light22-2.1.2.dist-info/RECORD
