Metadata-Version: 2.1
Name: excel-operate-light22
Version: 2.1.2
Summary: 方便快捷Excel操作
Home-page: https://github.com/18513233125/Excel-operate
Download-URL: https://pypi.org/project/excel-operate-light22
Author: 北极星光
Author-email: light22@126.com
License: MIT
Classifier: Programming Language :: Python :: 3
Classifier: License :: OSI Approved :: MIT License
Classifier: Operating System :: OS Independent
Requires-Python: >=3.6
License-File: LICENSE
Requires-Dist: openpyxl
